{
    "id": "bourns-cr0402-fx-5762glf",
    "reference": "R",
    "mpn": "CR0402-FX-5762GLF",
    "category": "Passive",
    "type": "SMT resistor",
    "datasheetUrl": null,
    "assets": {
        "blendfile": true,
        "symbol": true,
        "footprint": true
    },
    "blendfileId": "r-0402-1005metric",
    "symbolId": "r-57k6-0402",
    "footprintId": "r-0402-1005metric",
    "manufacturerId": "bourns",
    "tagIds": [
        "0402",
        "smt",
        "resistor",
        "passive"
    ]
}