{
    "reference": "D",
    "symbol": "STS321045B502",
    "footprint": "D_SOD-323",
    "datasheet": "https://www.eaton.com/content/dam/eaton/products/electronic-components/resources/data-sheet/eaton-sts321045b502-tvs-diode-esd-suppressor-data-sheet.pdf",
    "manufacturer": "Cooper Bussmann",
    "mpn": "STS321045B502",
    "description": null,
    "keywords": "DIODE, SEMICONDUCTOR, TVS, ESD",
    "displayName": null,
    "gitHub": null,
    "blender_model": "D_SOD-323",
    "pads": [
        {
            "reference": "1",
            "pin_name": "C",
            "alternate_pin_names": [],
            "electrical_type": "passive"
        },
        {
            "reference": "2",
            "pin_name": "A",
            "alternate_pin_names": [],
            "electrical_type": "passive"
        }
    ]
}