{
    "id": "taiyo-yuden-umk325bj105",
    "reference": "C",
    "mpn": "UMK325BJ105",
    "category": "Passive",
    "type": "SMT capacitor",
    "datasheetUrl": null,
    "assets": {
        "blendfile": true,
        "symbol": true,
        "footprint": true
    },
    "blendfileId": "c-1210-3225metric",
    "symbolId": "c-1u-1210",
    "footprintId": "c-1210-3225metric",
    "manufacturerId": "taiyo-yuden",
    "tagIds": [
        "1210",
        "smt",
        "capacitor",
        "passive",
        "ceramic",
        "mlcc"
    ]
}