{
    "id": "littelfuse-pgb1010603mr",
    "reference": "D",
    "mpn": "PGB1010603MR",
    "category": "Semiconductor",
    "type": "TVS diode",
    "datasheetUrl": null,
    "assets": {
        "blendfile": false,
        "symbol": false,
        "footprint": false
    },
    "blendfileId": "pgb1010603mr",
    "symbolId": "pgb1010603mr",
    "footprintId": "pgb1010603mr",
    "manufacturerId": "littelfuse",
    "tagIds": [
        "0603",
        "smt",
        "diode",
        "semiconductor",
        "tvs",
        "esd"
    ]
}